{
  "_type": "learning_stats::RegressionPrecession",
  "table": {
    "_type": "core::Table",
    "cols": [
      [
        135,
        148,
        148,
        136,
        119,
        104,
        118,
        115,
        126,
        141,
        135,
        125,
        149,
        170,
        170,
        158,
        133,
        114,
        140,
        145,
        150,
        178,
        163,
        172,
        178,
        199,
        199,
        184,
        162,
        146,
        166,
        171,
        180,
        193,
        181,
        183,
        218,
        230,
        242,
        209,
        191,
        172,
        194,
        196,
        196,
        236,
        235,
        229,
        264,
        272,
        237,
        211,
        180,
        201,
        204,
        188,
        235,
        227,
        234,
        264,
        302,
        293,
        259,
        229,
        203,
        229,
        242,
        233,
        267,
        269,
        270,
        315,
        364,
        347,
        312,
        274,
        237,
        278,
        284,
        277,
        317,
        313,
        318,
        374,
        413,
        405,
        355,
        306,
        271,
        306,
        315,
        301,
        356,
        348,
        355,
        422,
        465,
        467,
        404,
        347,
        305,
        336,
        340,
        362,
        348,
        363,
        435,
        491,
        505
      ],
      [
        135,
        148,
        148,
        136,
        119,
        104,
        118,
        115,
        126,
        141,
        135,
        125,
        149,
        170,
        170,
        158,
        133,
        114,
        140,
        145,
        150,
        178,
        163,
        172,
        178,
        199,
        199,
        184,
        162,
        146,
        166,
        171,
        180,
        193,
        181,
        183,
        218,
        230,
        242,
        209,
        191,
        172,
        194,
        196,
        196,
        236,
        235,
        229,
        264,
        272,
        237,
        211,
        180,
        201,
        204,
        188,
        235,
        227,
        234,
        264,
        302,
        293,
        259,
        229,
        203,
        229,
        242,
        233,
        267,
        269,
        270,
        315,
        364,
        347,
        312,
        274,
        237,
        278,
        284,
        277,
        317,
        313,
        318,
        374,
        413,
        405,
        355,
        306,
        271,
        306,
        315,
        301,
        356,
        348,
        355,
        422,
        465,
        467,
        404,
        347,
        305,
        336,
        340,
        362,
        348,
        363,
        435,
        491,
        505
      ],
      [
        73,
        72,
        72,
        72,
        73,
        74,
        74,
        74,
        73,
        72,
        72,
        72,
        73,
        72,
        71,
        71,
        73,
        75,
        74,
        73,
        72,
        71,
        71,
        72,
        72,
        71,
        71,
        72,
        73,
        74,
        74,
        73,
        72,
        71,
        72,
        72,
        71,
        70,
        70,
        72,
        74,
        75,
        73,
        72,
        72,
        70,
        70,
        71,
        71,
        70,
        71,
        73,
        75,
        77,
        75,
        74,
        74,
        72,
        72,
        72,
        70,
        69,
        71,
        74,
        76,
        76,
        74,
        73,
        72,
        71,
        71,
        71,
        68,
        68,
        70,
        73,
        76,
        75,
        73,
        72,
        71,
        70,
        70,
        69,
        66,
        66,
        69,
        73,
        76,
        75,
        72,
        72,
        69,
        69,
        69,
        66,
        63,
        63,
        67,
        72,
        77,
        75,
        73,
        73,
        71,
        72,
        71,
        66,
        63
      ]
    ],
    "meta": [
      {
        "_type": "core::NativeTableColumnMeta",
        "typeName": "core::int",
        "index": false,
        "min": 104,
        "max": 505
      },
      {
        "_type": "core::NativeTableColumnMeta",
        "typeName": "core::int",
        "index": false,
        "min": 104,
        "max": 505
      },
      {
        "_type": "core::NativeTableColumnMeta",
        "typeName": "core::int",
        "index": false,
        "min": 63,
        "max": 77
      }
    ]
  },
  "histogram": {
    "_type": "core::Table",
    "cols": [
      [
        30,
        71,
        112,
        153,
        194,
        235,
        276,
        317,
        358,
        399,
        440
      ],
      [
        71,
        112,
        153,
        194,
        235,
        276,
        317,
        358,
        399,
        440,
        481
      ],
      [
        15,
        20,
        15,
        17,
        14,
        9,
        10,
        4,
        1,
        3,
        1
      ],
      [
        13.761467889908257,
        18.34862385321101,
        13.761467889908257,
        15.596330275229358,
        12.844036697247706,
        8.256880733944953,
        9.174311926605505,
        3.669724770642202,
        0.9174311926605505,
        2.7522935779816513,
        0.9174311926605505
      ]
    ],
    "meta": [
      {
        "_type": "core::NativeTableColumnMeta",
        "typeName": "core::int",
        "index": false,
        "min": 30,
        "max": 440
      },
      {
        "_type": "core::NativeTableColumnMeta",
        "typeName": "core::int",
        "index": false,
        "min": 71,
        "max": 481
      },
      {
        "_type": "core::NativeTableColumnMeta",
        "typeName": "core::int",
        "index": false,
        "min": 1,
        "max": 20
      },
      {
        "_type": "core::NativeTableColumnMeta",
        "typeName": "core::float",
        "index": false,
        "min": 0.9174311926605505,
        "max": 18.34862385321101
      }
    ]
  },
  "boxplot": {
    "_type": "util::BoxPlotInt",
    "min": 30,
    "max": 442,
    "whiskerLow": -127,
    "whiskerHigh": 460,
    "percentile1": 30,
    "percentile5": 39,
    "percentile25": 93,
    "percentile50": 157,
    "percentile75": 240,
    "percentile95": 354,
    "percentile99": 424,
    "countOutliersLow": 0,
    "countOutliersHigh": 0,
    "percentageOutliersLow": 0,
    "percentageOutliersHigh": 0,
    "sum": 19111,
    "avg": 175.3302752293578,
    "std": 95.0781408696018,
    "size": 109
  }
}